pytypes/__init__.py
pytypes/exceptions.py
pytypes/py.typed
pytypes/stubfile_2_converter.py
pytypes/stubfile_manager.py
pytypes/type_util.py
pytypes/typechecker.py
pytypes/typechecker.pyi
pytypes/typecomment_parser.py
pytypes/typelogger.py
pytypes/util.py
pytypes-1.0b10.dist-info/LICENSE
pytypes-1.0b10.dist-info/METADATA
pytypes-1.0b10.dist-info/NOTICE
pytypes-1.0b10.dist-info/WHEEL
pytypes-1.0b10.dist-info/entry_points.txt
pytypes-1.0b10.dist-info/top_level.txt
pytypes-1.0b10.dist-info/RECORD
