Metadata-Version: 1.1
Name: pytypes
Version: 1.0b10
Summary: Typing toolbox for Python 3 _and_ 2.
Home-page: https://github.com/Stewori/pytypes
Author: Stefan Richthofer
Author-email: stefan.richthofer@jyni.org
License: Apache-2.0
Platform: UNKNOWN
Classifier: Development Status :: 4 - Beta
Classifier: Intended Audience :: Developers
Classifier: License :: OSI Approved :: Apache Software License
Classifier: Programming Language :: Python
Classifier: Programming Language :: Python :: 2
Classifier: Programming Language :: Python :: 2.7
Classifier: Programming Language :: Python :: 3
Classifier: Programming Language :: Python :: 3.5
Classifier: Programming Language :: Python :: 3.6
Classifier: Programming Language :: Python :: 3.7
Classifier: Programming Language :: Python :: 3.8
